py_fake_useragent/__init__.py
py_fake_useragent/exceptions.py
py_fake_useragent/lib/useragent.dylib
py_fake_useragent/lib/useragent.h
py_fake_useragent-0.1.0.dist-info/METADATA
py_fake_useragent-0.1.0.dist-info/WHEEL
py_fake_useragent-0.1.0.dist-info/top_level.txt
py_fake_useragent-0.1.0.dist-info/RECORD
