Metadata-Version: 2.4
Name: py-fake-useragent
Version: 0.1.0
Summary: Генерация User-Agent и HTTP-заголовков на ядре Go
License-Expression: MIT
Project-URL: Homepage, https://github.com/imbecility/go-fake-useragent
Classifier: Programming Language :: Python :: 3
Classifier: Programming Language :: Go
Classifier: Operating System :: OS Independent
Requires-Python: >=3.10
